README.md
setup.py
gbrpi/__init__.py
gbrpi.egg-info/PKG-INFO
gbrpi.egg-info/SOURCES.txt
gbrpi.egg-info/dependency_links.txt
gbrpi.egg-info/requires.txt
gbrpi.egg-info/top_level.txt
gbrpi/constants/rs232.py
gbrpi/constants/types.py
gbrpi/electronics/gpio_device.py
gbrpi/electronics/led_ring.py
gbrpi/net/rs232_connection.py
gbrpi/net/table_conn.py