Metadata-Version: 1.1
Name: gbrpi
Version: 0.0.3
Summary: A python library for Raspberry Pi operations used for FRC
Home-page: https://github.com/GreenBlitz/GBRPi
Author: Ido Heinemann
Author-email: idohaineman@gmail.com
License: Apache License 2.0
Download-URL: https://github.com/GreenBlitz/GBRPi/archive/v0.0.3.tar.gz
Keywords: rpi,raspberry pi,frc
Platform: UNKNOWN
Classifier: Development Status :: 3 - Alpha
Classifier: Intended Audience :: Developers
Classifier: Programming Language :: Python :: 3
Classifier: Programming Language :: Python :: 3.4
Classifier: Programming Language :: Python :: 3.5
Classifier: Programming Language :: Python :: 3.6
Classifier: Programming Language :: Python :: 3.7
Classifier: Programming Language :: Python :: 3.8
